pygatttool/__init__.py
pygatttool/_pygatttool.py
pygatttool-0.1.1.dist-info/METADATA
pygatttool-0.1.1.dist-info/WHEEL
pygatttool-0.1.1.dist-info/RECORD
