Metadata-Version: 2.1
Name: pygatttool
Version: 0.1.1
Summary: BLE client package wrapping gatttool
Home-page: https://github.com/wideopensource/pygatttool
License: MIT
Author: wideopentech
Author-email: fossie@wideoppentech.co.uk
Requires-Python: >=3.8,<4.0
Classifier: License :: OSI Approved :: MIT License
Classifier: Operating System :: POSIX :: Linux
Classifier: Programming Language :: Python :: 3
Classifier: Programming Language :: Python :: 3.8
Classifier: Programming Language :: Python :: 3.9
Classifier: Programming Language :: Python :: 3.10
Classifier: Programming Language :: Python :: 3.11
Classifier: Programming Language :: Python :: 3
Requires-Dist: pexpect (>=4.8.0,<5.0.0)
Project-URL: Repository, https://github.com/wideopensource/pygatttool
